qt_brohub-0.0.4.dist-info/LICENSE
qt_brohub-0.0.4.dist-info/top_level.txt
qt_brohub-0.0.4.dist-info/RECORD
qt_brohub-0.0.4.dist-info/METADATA
qt_brohub-0.0.4.dist-info/WHEEL
brohub/utils.cpython-312-i386-linux-gnu.so
brohub/broker_base.c
brohub/broker.cpython-312-i386-linux-gnu.so
brohub/utils.pyx
brohub/brokers.pyx
brohub/broker_base.pyx
brohub/compiled.c
brohub/compiled.cpython-312-i386-linux-gnu.so
brohub/broker.c
brohub/broker_degiro.c
brohub/plain.py
brohub/broker.pyx
brohub/broker_degiro.cpython-312-i386-linux-gnu.so
brohub/broker_base.cpython-312-i386-linux-gnu.so
brohub/compiled.pyx
brohub/broker_factory.c
brohub/brokers.c
brohub/broker_degiro.pyx
brohub/utils.c
brohub/brokers.cpython-312-i386-linux-gnu.so
brohub/broker_factory.cpython-312-i386-linux-gnu.so
brohub/__init__.py
brohub/py.typed
brohub/broker_factory.pyx
brohub/compiled.pyi
